enrichwrap/__init__.py
enrichwrap/ccexception.py
enrichwrap/command_line.py
enrichwrap/generate_ds2_id_code.py
enrichwrap/generate_python_id_code.py
enrichwrap/indata.py
enrichwrap/listexternal.py
enrichwrap/main.py
enrichwrap/poor_logging.py
enrichwrap/read_mappings.py
enrichwrap/runsteps.py
enrichwrap/steps.py
enrichwrap/targets.py
enrichwrap/tosas.py
enrichwrap/trial.py
enrichwrap/samples/json_dict.json
enrichwrap/samples/sample_input.json
enrichwrap/samples/sample_steps.json
enrichwrap/xml/biocatch_getscore_payload.xml
enrichwrap/xml/biocatch_init_payload.xml
enrichwrap/xml/biocatch_to_sas.xml
enrichwrap/xml/boku_gpir_payload.xml
enrichwrap/xml/boku_gpir_to_sas.xml
enrichwrap/xml/boku_maa_payload.xml
enrichwrap/xml/boku_maa_to_sas.xml
enrichwrap/xml/common_to_sas.xml
enrichwrap/xml/datavisor_payload.xml
enrichwrap/xml/datavisor_to_sas.xml
enrichwrap/xml/giact_payload.xml
enrichwrap/xml/giact_to_sas.xml
enrichwrap/xml/iovation_payload.xml
enrichwrap/xml/iovation_to_sas.xml
enrichwrap/xml/payfone_payload.xml
enrichwrap/xml/payfone_to_sas.xml
enrichwrap/xml/socure_payload.xml
enrichwrap/xml/socure_to_sas.xml
enrichwrap-0.0.64.data/scripts/enrichwrap
enrichwrap-0.0.64.dist-info/LICENSE
enrichwrap-0.0.64.dist-info/METADATA
enrichwrap-0.0.64.dist-info/WHEEL
enrichwrap-0.0.64.dist-info/entry_points.txt
enrichwrap-0.0.64.dist-info/top_level.txt
enrichwrap-0.0.64.dist-info/RECORD
