Metadata-Version: 2.1
Name: enrichwrap
Version: 0.0.64
Summary: A small package testing calling out to third party enrichment
Home-page: http://github.com/suhens/enrichwrap
Author: Sue Hannum
Author-email: Sue.Hannum@sas.com
Keywords: enrichment
Classifier: Development Status :: 3 - Alpha
Classifier: Intended Audience :: Developers
Classifier: Programming Language :: Python :: 3
Classifier: Operating System :: OS Independent
Classifier: Topic :: Text Processing :: Linguistic
Requires-Python: >=3.6
License-File: LICENSE
Requires-Dist: requests
Requires-Dist: markdown
